pyblu/__init__.py
pyblu/entities.py
pyblu/errors.py
pyblu/parse.py
pyblu/player.py
pyblu/py.typed
pyblu-2.0.5.dist-info/METADATA
pyblu-2.0.5.dist-info/WHEEL
pyblu-2.0.5.dist-info/licenses/LICENSE
pyblu-2.0.5.dist-info/RECORD
