Metadata-Version: 2.4
Name: pyblu
Version: 2.0.5
Project-URL: repository, https://github.com/LouisChrist/pyblu
Author-email: Louis Christ <mail@louischrist.de>
License-Expression: MIT
License-File: LICENSE
Requires-Dist: aiohttp>=3.11.11
Requires-Dist: lxml>=5.0.0
